LICENSE
MANIFEST.in
README.md
README.rst
setup.py
binsel/__init__.py
binsel/binsel_hardvote.py
binsel/bootstrap_solutions.py
binsel/enumerate_negations.py
binsel/fltsel_search.py
binsel/hard_voting.py
binsel/negate_bool_features.py
binsel.egg-info/PKG-INFO
binsel.egg-info/SOURCES.txt
binsel.egg-info/dependency_links.txt
binsel.egg-info/requires.txt
binsel.egg-info/top_level.txt
binsel.egg-info/zip-safe
test/__init__.py
test/test_hard_voting.py
test/test_negate_bool_features.py