Metadata-Version: 2.1
Name: binsel
Version: 0.3.2
Summary: Feature selection for Hard Voting classifier
Home-page: https://github.com/ulf1/maxjoshua
Author: Ulf Hamster
Author-email: 554c46@gmail.com
License: Apache License 2.0
Requires-Python: >=3.6
License-File: LICENSE
